k_torch/__init__.py
k_torch/history.py
k_torch/initializers.py
k_torch/layers.py
k_torch/models.py
k_torch/optimizers.py
k_torch/test.py
k_torch-0.1.1.dist-info/LICENSE
k_torch-0.1.1.dist-info/METADATA
k_torch-0.1.1.dist-info/WHEEL
k_torch-0.1.1.dist-info/top_level.txt
k_torch-0.1.1.dist-info/RECORD
