Metadata-Version: 2.1
Name: k-torch
Version: 0.1.1
Summary: A Keras-like wrapper for PyTorch
Home-page: https://github.com/daroodar/k_torch
Author: Osama dar, Muhammad Ismail
Author-email: osamadar1996@gmail.com
License: UNKNOWN
Platform: UNKNOWN
Classifier: Programming Language :: Python :: 3
Classifier: License :: OSI Approved :: MIT License
Classifier: Operating System :: OS Independent
